.gitignore
CHANGES.txt
MANIFEST.in
README.rst
bootstrap.py
buildout.cfg
development.ini
setup.cfg
setup.py
kotti_solr/__init__.py
kotti_solr/events.py
kotti_solr.egg-info/PKG-INFO
kotti_solr.egg-info/SOURCES.txt
kotti_solr.egg-info/dependency_links.txt
kotti_solr.egg-info/not-zip-safe
kotti_solr.egg-info/requires.txt
kotti_solr.egg-info/top_level.txt
kotti_solr/tests/conftest.py
kotti_solr/tests/test_events.py
kotti_solr/tests/test_solr.py